{"created_at":"Sun Feb 16 21:58:21 +0000 2020","id":1229163128916590592,"id_str":"1229163128916590592","text":"RT @cjhiking: \u65b0\u578b\u30b3\u30ed\u30ca\u3067\u4ee5\u524d\u304b\u3089\u7591\u308f\u308c\u3066\u3044\u308b\u6297\u4f53\u4f9d\u5b58\u6027\u611f\u67d3\u5897\u5f37\n\u7dcf\u8aac\u7b49\u3092\u307e\u3068\u3081\u308b\u3068\n\u4e0d\u5341\u5206\u306a\u6297\u4f53\u304c\u3067\u304d\u308b\u30682\u5ea6\u76ee\u306e\u611f\u67d3\u3084\u611f\u67d3\u5f8c\u671f\u3067\n\u30a6\u30a3\u30eb\u30b9\/\u6297\u4f53\u8907\u5408\u4f53\u304c\u514d\u75ab\u7d30\u80de\u306b\u6297\u4f53\u30ec\u30bb\u30d7\u30bf\u30fc\u3092\u901a\u3057\u3066\u611f\u67d3\u3057\u514d\u75ab\u7cfb\u306e\u6df7\u4e71\u3092\u62db\u304f\u4e8b\u3068\n\u30c7\u30f3\u30b0\u30a6\u30a3\u30eb\u30b9\u3067\u6709\u540d\u3060\u304c\u732b\u30b3\u30ed\u30ca\u3084SARS\u3067\u3082\u2026","source":"\u003ca href=\"http:\/\/twitter.com\/#!\/download\/ipad\" rel=\"nofollow\"\u003eTwitter for iPad\u003c\/a\u003e","truncated":false,"in_reply_to_status_id":null,"in_reply_to_status_id_str":null,"in_reply_to_user_id":null,"in_reply_to_user_id_str":null,"in_reply_to_screen_name":null,"user":{"id":145596480,"id_str":"145596480","name":"\u3057\u3083\u308b\u3068\u308a\u3085\u305a\u30ed\u30c3\u30af\u306e\u307f\u306a\u9686\u4e00\u3002","screen_name":"leizoko","location":"\u5343\u8449","url":null,"description":"\u4f55\u4e8b\u304b\u8d77\u304d\u3066\u3082\u524d\u5411\u304d\u306b\u7b11\u3063\u3066\u3044\u304d\u305f\u3044\u8005\u3002\uff08\u8aad\u307f\u305f\u3044\u30c3\uff01\u305f\u3081\u306b\u306a\u308b\uff6f\uff01\u3002\u3046\u308e\u3001\u3081\u3063\u3061\u3083\u304a\u3082\u308d\u3043\u3058\u3083\u3093\u3053\u308c\u3063\uff01\uff01\u3068\u3001\u611f\u3058\u305f\u5834\u5408\u6050\u308c\u5165\u308a\u307e\u3059\u304c\uff8c\uff6b\uff9b-\u3057\u3066\u3057\u307e\u3044\u307e\u3059\u4f55\u5352^O^)\/ \u3002 \uff09\u6ce8\u610f\uff1a\u79c1\u306f\u3042\u304f\u306e\u5f37\u3044\u7b11\u3044\u3082\u597d\u307f\u307e\u3059\u3086\u3048\u3001\u541f\u5473\u4e14\u3064\u3054\u582a\u80fd\u3057\u3066\u307f\u3066\u306f\u3044\u304b\u304c\u3067\u3057\u3087\u3046\u304b\uff9f\u0414\uff9f)\u7b11\u3002[\u8131\u539f\u767a]\u306a\u3093\u306e\u8e8a\u8e87\u3044\u3082\u306a\u304f\u55b0\u3044\u305f\u3044\u3093\u3060\u3002","translator_type":"none","protected":false,"verified":false,"followers_count":731,"friends_count":2069,"listed_count":13,"favourites_count":22471,"statuses_count":47112,"created_at":"Wed May 19 10:45:06 +0000 2010","utc_offset":null,"time_zone":null,"geo_enabled":false,"lang":null,"contributors_enabled":false,"is_translator":false,"profile_background_color":"C0DEED","profile_background_image_url":"http:\/\/abs.twimg.com\/images\/themes\/theme1\/bg.png","profile_background_image_url_https":"https:\/\/abs.twimg.com\/images\/themes\/theme1\/bg.png","profile_background_tile":false,"profile_link_color":"1DA1F2","profile_sidebar_border_color":"C0DEED","profile_sidebar_fill_color":"DDEEF6","profile_text_color":"333333","profile_use_background_image":true,"profile_image_url":"http:\/\/pbs.twimg.com\/profile_images\/729407100749635586\/LRQa2mnn_normal.jpg","profile_image_url_https":"https:\/\/pbs.twimg.com\/profile_images\/729407100749635586\/LRQa2mnn_normal.jpg","profile_banner_url":"https:\/\/pbs.twimg.com\/profile_banners\/145596480\/1469754833","default_profile":true,"default_profile_image":false,"following":null,"follow_request_sent":null,"notifications":null},"geo":null,"coordinates":null,"place":null,"contributors":null,"retweeted_status":{"created_at":"Sun Feb 16 09:46:12 +0000 2020","id":1228978876639875072,"id_str":"1228978876639875072","text":"\u65b0\u578b\u30b3\u30ed\u30ca\u3067\u4ee5\u524d\u304b\u3089\u7591\u308f\u308c\u3066\u3044\u308b\u6297\u4f53\u4f9d\u5b58\u6027\u611f\u67d3\u5897\u5f37\n\u7dcf\u8aac\u7b49\u3092\u307e\u3068\u3081\u308b\u3068\n\u4e0d\u5341\u5206\u306a\u6297\u4f53\u304c\u3067\u304d\u308b\u30682\u5ea6\u76ee\u306e\u611f\u67d3\u3084\u611f\u67d3\u5f8c\u671f\u3067\n\u30a6\u30a3\u30eb\u30b9\/\u6297\u4f53\u8907\u5408\u4f53\u304c\u514d\u75ab\u7d30\u80de\u306b\u6297\u4f53\u30ec\u30bb\u30d7\u30bf\u30fc\u3092\u901a\u3057\u3066\u611f\u67d3\u3057\u514d\u75ab\u7cfb\u306e\u6df7\u4e71\u3092\u62db\u304f\u4e8b\u3068\n\u30c7\u30f3\u30b0\u30a6\u30a3\u30eb\u30b9\u3067\u6709\u540d\u3060\u304c\u732b\u2026 https:\/\/t.co\/41jXPAC1gp","display_text_range":[0,140],"source":"\u003ca href=\"https:\/\/mobile.twitter.com\" rel=\"nofollow\"\u003eTwitter Web App\u003c\/a\u003e","truncated":true,"in_reply_to_status_id":null,"in_reply_to_status_id_str":null,"in_reply_to_user_id":null,"in_reply_to_user_id_str":null,"in_reply_to_screen_name":null,"user":{"id":703868384174145536,"id_str":"703868384174145536","name":"motihamotiya2","screen_name":"cjhiking","location":null,"url":null,"description":"\u66b4\u843d\u6642\u4ee5\u5916\u306f\u30d8\u30c3\u30b8\u591a\u76ee\u3002\u30ea\u30b9\u30af\u4f4e\u3081\u306b\u3084\u3063\u3066\u3044\u308b\u517c\u696d\u3002\u7b2c\u4e00\u6b21\u30a2\u30d9\u30ce\u30df\u30af\u30b9\u7d42\u4e86\u76f4\u5f8c300\u4e07\u30b9\u30bf\u30fc\u30c818\u5e743\u6708\u306b\u5104\u3054\u3048\u3002\u6700\u8fd1\u306f\u8d64\u5b57\u30d0\u30a4\u30aa\u306e\u904e\u53bb\u306e\u76f8\u5834\u30d1\u30bf\u30f3\u8e0f\u8972\u58f2\u8cb7\u4e2d\u5fc3\u3002\u7d71\u8a08\u7684\u30a8\u30d3\u30c7\u30f3\u30b9,\u4ed6\u4eba\u306b\u60c5\u5831\u9762\u3067\u512a\u4f4d\u6027\u304c\u3042\u308b\u5834\u3067\u306e\u58f2\u8cb7\u91cd\u8996\u3002\u8a71\u3057\u304b\u3051\u3089\u308c\u3066\u3082\u7a2e\u3005\u306e\u7406\u7531\u3067\u3044\u3044\u306d\u3060\u3051\u8fd4\u3057\u305f\u308a\u3059\u308b\u4e8b\u304c\u5927\u534a\u3068\u601d\u3044\u307e\u3059\u304c\u4ed6\u610f\u306f\u5168\u304f\u3042\u308a\u307e\u305b\u3093","translator_type":"none","protected":false,"verified":false,"followers_count":10223,"friends_count":70,"listed_count":208,"favourites_count":31079,"statuses_count":2812,"created_at":"Sun Feb 28 09:04:34 +0000 2016","utc_offset":null,"time_zone":null,"geo_enabled":false,"lang":null,"contributors_enabled":false,"is_translator":false,"profile_background_color":"F5F8FA","profile_background_image_url":"","profile_background_image_url_https":"","profile_background_tile":false,"profile_link_color":"1DA1F2","profile_sidebar_border_color":"C0DEED","profile_sidebar_fill_color":"DDEEF6","profile_text_color":"333333","profile_use_background_image":true,"profile_image_url":"http:\/\/pbs.twimg.com\/profile_images\/846953262955839493\/iuqqoLDh_normal.jpg","profile_image_url_https":"https:\/\/pbs.twimg.com\/profile_images\/846953262955839493\/iuqqoLDh_normal.jpg","profile_banner_url":"https:\/\/pbs.twimg.com\/profile_banners\/703868384174145536\/1522588085","default_profile":true,"default_profile_image":false,"following":null,"follow_request_sent":null,"notifications":null},"geo":null,"coordinates":null,"place":null,"contributors":null,"quoted_status_id":1228556843057725441,"quoted_status_id_str":"1228556843057725441","quoted_status":{"created_at":"Sat Feb 15 05:49:11 +0000 2020","id":1228556843057725441,"id_str":"1228556843057725441","text":"\u91cd\u8981\u306a\u306e\u3067\u8981\u7d04\u3059\u308b\u3002\u6b66\u6f22\u533b\u5e2b\u304c\u82f1\u56fd\u306e\u89aa\u65cf\u306b\u8a9e\u3063\u305f\u5185\u5bb9\u306b\u3088\u308b\u3068\u3001\u30b3\u30ed\u30ca\u30a6\u30a3\u30eb\u30b9\u6cbb\u7652\u5f8c\u306b2\u5ea6\u76ee\u306b\u611f\u67d3\u3059\u308b\u5834\u5408\u304c\u3042\u308a\u3001\u4e00\u5ea6\u76ee\u306e\u6cbb\u7642\u85ac\u304c\u5fc3\u81d3\u7d44\u7e54\u306b\u4e0e\u3048\u305f\u30c0\u30e1\u30fc\u30b8\u3067\u3001\u6297\u4f53\u304c\u6a5f\u80fd\u305b\u305a\u5fc3\u75be\u60a3\u306b\u3088\u308a\u7a81\u7136\u6b7b\u3059\u308b\u30b1\u30fc\u30b9\u304c\u3042\u308b\u3002\uff08\u7d9a\u300cExclusive\u2026 https:\/\/t.co\/NDnC0FfX14","source":"\u003ca href=\"http:\/\/twitter.com\/download\/iphone\" rel=\"nofollow\"\u003eTwitter for iPhone\u003c\/a\u003e","truncated":true,"in_reply_to_status_id":null,"in_reply_to_status_id_str":null,"in_reply_to_user_id":null,"in_reply_to_user_id_str":null,"in_reply_to_screen_name":null,"user":{"id":509922519,"id_str":"509922519","name":"\u68ee\u5ca1\u6b63\u535a","screen_name":"Sukuitohananika","location":"\u30a6\u30a7\u30d6\u30b5\u30a4\u30c8\u2192","url":"http:\/\/www.lifestudies.org\/jp","description":"\u54f2\u5b66\u8005\u3002\u65e9\u7a32\u7530\u5927\u5b66\u4eba\u9593\u79d1\u5b66\u90e8\u6559\u6388\u3002\u751f\u547d\u306e\u54f2\u5b66\u3001\u5f62\u800c\u4e0a\u5b66\u3001\u751f\u547d\u5b66\u3001\u502b\u7406\u5b66\u3002\u300e\u7121\u75db\u6587\u660e\u8ad6\u300f\u300e\u307e\u3093\u304c\u54f2\u5b66\u5165\u9580\u300f\u300e\u611f\u3058\u306a\u3044\u7537\u300f\u300e\u5b97\u6559\u306a\u304d\u6642\u4ee3\u3092\u751f\u304d\u308b\u305f\u3081\u306b\u300f\u3002\u751f\u547d\u306e\u54f2\u5b66\u306b\u3064\u3044\u3066\u306e\u672c\u3092\u57f7\u7b46\u4e2d\u3002Masahiro Morioka. Philosopher. Professor, Waseda University.","translator_type":"none","protected":false,"verified":false,"followers_count":15158,"friends_count":155,"listed_count":724,"favourites_count":25,"statuses_count":25412,"created_at":"Thu Mar 01 08:33:53 +0000 2012","utc_offset":null,"time_zone":null,"geo_enabled":false,"lang":null,"contributors_enabled":false,"is_translator":false,"profile_background_color":"9AE4E8","profile_background_image_url":"http:\/\/abs.twimg.com\/images\/themes\/theme16\/bg.gif","profile_background_image_url_https":"https:\/\/abs.twimg.com\/images\/themes\/theme16\/bg.gif","profile_background_tile":false,"profile_link_color":"0084B4","profile_sidebar_border_color":"BDDCAD","profile_sidebar_fill_color":"DDFFCC","profile_text_color":"333333","profile_use_background_image":true,"profile_image_url":"http:\/\/pbs.twimg.com\/profile_images\/1005425357774729219\/J5qrarEc_normal.jpg","profile_image_url_https":"https:\/\/pbs.twimg.com\/profile_images\/1005425357774729219\/J5qrarEc_normal.jpg","profile_banner_url":"https:\/\/pbs.twimg.com\/profile_banners\/509922519\/1373647669","default_profile":false,"default_profile_image":false,"following":null,"follow_request_sent":null,"notifications":null},"geo":null,"coordinates":null,"place":null,"contributors":null,"is_quote_status":false,"extended_tweet":{"full_text":"\u91cd\u8981\u306a\u306e\u3067\u8981\u7d04\u3059\u308b\u3002\u6b66\u6f22\u533b\u5e2b\u304c\u82f1\u56fd\u306e\u89aa\u65cf\u306b\u8a9e\u3063\u305f\u5185\u5bb9\u306b\u3088\u308b\u3068\u3001\u30b3\u30ed\u30ca\u30a6\u30a3\u30eb\u30b9\u6cbb\u7652\u5f8c\u306b2\u5ea6\u76ee\u306b\u611f\u67d3\u3059\u308b\u5834\u5408\u304c\u3042\u308a\u3001\u4e00\u5ea6\u76ee\u306e\u6cbb\u7642\u85ac\u304c\u5fc3\u81d3\u7d44\u7e54\u306b\u4e0e\u3048\u305f\u30c0\u30e1\u30fc\u30b8\u3067\u3001\u6297\u4f53\u304c\u6a5f\u80fd\u305b\u305a\u5fc3\u75be\u60a3\u306b\u3088\u308a\u7a81\u7136\u6b7b\u3059\u308b\u30b1\u30fc\u30b9\u304c\u3042\u308b\u3002\uff08\u7d9a\u300cExclusive: Chinese doctors say Wuhan coronavi https:\/\/t.co\/lzxlbrTMQ0","display_text_range":[0,175],"entities":{"hashtags":[],"urls":[{"url":"https:\/\/t.co\/lzxlbrTMQ0","expanded_url":"https:\/\/www.taiwannews.com.tw\/en\/news\/3876197","display_url":"taiwannews.com.tw\/en\/news\/3876197","indices":[152,175]}],"user_mentions":[],"symbols":[]}},"quote_count":304,"reply_count":48,"retweet_count":5311,"favorite_count":6493,"entities":{"hashtags":[],"urls":[{"url":"https:\/\/t.co\/NDnC0FfX14","expanded_url":"https:\/\/twitter.com\/i\/web\/status\/1228556843057725441","display_url":"twitter.com\/i\/web\/status\/1\u2026","indices":[117,140]}],"user_mentions":[],"symbols":[]},"favorited":false,"retweeted":false,"possibly_sensitive":false,"filter_level":"low","lang":"ja"},"quoted_status_permalink":{"url":"https:\/\/t.co\/7OXhunLBNo","expanded":"https:\/\/twitter.com\/Sukuitohananika\/status\/1228556843057725441","display":"twitter.com\/Sukuitohananik\u2026"},"is_quote_status":true,"extended_tweet":{"full_text":"\u65b0\u578b\u30b3\u30ed\u30ca\u3067\u4ee5\u524d\u304b\u3089\u7591\u308f\u308c\u3066\u3044\u308b\u6297\u4f53\u4f9d\u5b58\u6027\u611f\u67d3\u5897\u5f37\n\u7dcf\u8aac\u7b49\u3092\u307e\u3068\u3081\u308b\u3068\n\u4e0d\u5341\u5206\u306a\u6297\u4f53\u304c\u3067\u304d\u308b\u30682\u5ea6\u76ee\u306e\u611f\u67d3\u3084\u611f\u67d3\u5f8c\u671f\u3067\n\u30a6\u30a3\u30eb\u30b9\/\u6297\u4f53\u8907\u5408\u4f53\u304c\u514d\u75ab\u7d30\u80de\u306b\u6297\u4f53\u30ec\u30bb\u30d7\u30bf\u30fc\u3092\u901a\u3057\u3066\u611f\u67d3\u3057\u514d\u75ab\u7cfb\u306e\u6df7\u4e71\u3092\u62db\u304f\u4e8b\u3068\n\u30c7\u30f3\u30b0\u30a6\u30a3\u30eb\u30b9\u3067\u6709\u540d\u3060\u304c\u732b\u30b3\u30ed\u30ca\u3084SARS\u3067\u3082\u7591\u308f\u308c\u3066\u3044\u305f\u3068\n(https:\/\/t.co\/gP01s1H5Vd https:\/\/t.co\/0NQXnwHCtc","display_text_range":[0,157],"entities":{"hashtags":[],"urls":[{"url":"https:\/\/t.co\/gP01s1H5Vd","expanded_url":"https:\/\/onlinelibrary.wiley.com\/doi\/pdf\/10.1111\/imr.12367","display_url":"onlinelibrary.wiley.com\/doi\/pdf\/10.111\u2026","indices":[134,157]}],"user_mentions":[],"symbols":[],"media":[{"id":1228978843588775936,"id_str":"1228978843588775936","indices":[158,181],"media_url":"http:\/\/pbs.twimg.com\/media\/EQ41vzCUUAANBlE.png","media_url_https":"https:\/\/pbs.twimg.com\/media\/EQ41vzCUUAANBlE.png","url":"https:\/\/t.co\/0NQXnwHCtc","display_url":"pic.twitter.com\/0NQXnwHCtc","expanded_url":"https:\/\/twitter.com\/cjhiking\/status\/1228978876639875072\/photo\/1","type":"photo","sizes":{"small":{"w":583,"h":680,"resize":"fit"},"medium":{"w":750,"h":875,"resize":"fit"},"large":{"w":750,"h":875,"resize":"fit"},"thumb":{"w":150,"h":150,"resize":"crop"}}},{"id":1228978843609780224,"id_str":"1228978843609780224","indices":[158,181],"media_url":"http:\/\/pbs.twimg.com\/media\/EQ41vzHU0AArHHi.jpg","media_url_https":"https:\/\/pbs.twimg.com\/media\/EQ41vzHU0AArHHi.jpg","url":"https:\/\/t.co\/0NQXnwHCtc","display_url":"pic.twitter.com\/0NQXnwHCtc","expanded_url":"https:\/\/twitter.com\/cjhiking\/status\/1228978876639875072\/photo\/1","type":"photo","sizes":{"thumb":{"w":150,"h":150,"resize":"crop"},"medium":{"w":761,"h":987,"resize":"fit"},"small":{"w":524,"h":680,"resize":"fit"},"large":{"w":761,"h":987,"resize":"fit"}}},{"id":1228978843593011200,"id_str":"1228978843593011200","indices":[158,181],"media_url":"http:\/\/pbs.twimg.com\/media\/EQ41vzDU8AAfbzG.png","media_url_https":"https:\/\/pbs.twimg.com\/media\/EQ41vzDU8AAfbzG.png","url":"https:\/\/t.co\/0NQXnwHCtc","display_url":"pic.twitter.com\/0NQXnwHCtc","expanded_url":"https:\/\/twitter.com\/cjhiking\/status\/1228978876639875072\/photo\/1","type":"photo","sizes":{"medium":{"w":884,"h":714,"resize":"fit"},"small":{"w":680,"h":549,"resize":"fit"},"large":{"w":884,"h":714,"resize":"fit"},"thumb":{"w":150,"h":150,"resize":"crop"}}},{"id":1228978843605536769,"id_str":"1228978843605536769","indices":[158,181],"media_url":"http:\/\/pbs.twimg.com\/media\/EQ41vzGUEAEnuS3.png","media_url_https":"https:\/\/pbs.twimg.com\/media\/EQ41vzGUEAEnuS3.png","url":"https:\/\/t.co\/0NQXnwHCtc","display_url":"pic.twitter.com\/0NQXnwHCtc","expanded_url":"https:\/\/twitter.com\/cjhiking\/status\/1228978876639875072\/photo\/1","type":"photo","sizes":{"medium":{"w":1035,"h":713,"resize":"fit"},"large":{"w":1035,"h":713,"resize":"fit"},"small":{"w":680,"h":468,"resize":"fit"},"thumb":{"w":150,"h":150,"resize":"crop"}}}]},"extended_entities":{"media":[{"id":1228978843588775936,"id_str":"1228978843588775936","indices":[158,181],"media_url":"http:\/\/pbs.twimg.com\/media\/EQ41vzCUUAANBlE.png","media_url_https":"https:\/\/pbs.twimg.com\/media\/EQ41vzCUUAANBlE.png","url":"https:\/\/t.co\/0NQXnwHCtc","display_url":"pic.twitter.com\/0NQXnwHCtc","expanded_url":"https:\/\/twitter.com\/cjhiking\/status\/1228978876639875072\/photo\/1","type":"photo","sizes":{"small":{"w":583,"h":680,"resize":"fit"},"medium":{"w":750,"h":875,"resize":"fit"},"large":{"w":750,"h":875,"resize":"fit"},"thumb":{"w":150,"h":150,"resize":"crop"}}},{"id":1228978843609780224,"id_str":"1228978843609780224","indices":[158,181],"media_url":"http:\/\/pbs.twimg.com\/media\/EQ41vzHU0AArHHi.jpg","media_url_https":"https:\/\/pbs.twimg.com\/media\/EQ41vzHU0AArHHi.jpg","url":"https:\/\/t.co\/0NQXnwHCtc","display_url":"pic.twitter.com\/0NQXnwHCtc","expanded_url":"https:\/\/twitter.com\/cjhiking\/status\/1228978876639875072\/photo\/1","type":"photo","sizes":{"thumb":{"w":150,"h":150,"resize":"crop"},"medium":{"w":761,"h":987,"resize":"fit"},"small":{"w":524,"h":680,"resize":"fit"},"large":{"w":761,"h":987,"resize":"fit"}}},{"id":1228978843593011200,"id_str":"1228978843593011200","indices":[158,181],"media_url":"http:\/\/pbs.twimg.com\/media\/EQ41vzDU8AAfbzG.png","media_url_https":"https:\/\/pbs.twimg.com\/media\/EQ41vzDU8AAfbzG.png","url":"https:\/\/t.co\/0NQXnwHCtc","display_url":"pic.twitter.com\/0NQXnwHCtc","expanded_url":"https:\/\/twitter.com\/cjhiking\/status\/1228978876639875072\/photo\/1","type":"photo","sizes":{"medium":{"w":884,"h":714,"resize":"fit"},"small":{"w":680,"h":549,"resize":"fit"},"large":{"w":884,"h":714,"resize":"fit"},"thumb":{"w":150,"h":150,"resize":"crop"}}},{"id":1228978843605536769,"id_str":"1228978843605536769","indices":[158,181],"media_url":"http:\/\/pbs.twimg.com\/media\/EQ41vzGUEAEnuS3.png","media_url_https":"https:\/\/pbs.twimg.com\/media\/EQ41vzGUEAEnuS3.png","url":"https:\/\/t.co\/0NQXnwHCtc","display_url":"pic.twitter.com\/0NQXnwHCtc","expanded_url":"https:\/\/twitter.com\/cjhiking\/status\/1228978876639875072\/photo\/1","type":"photo","sizes":{"medium":{"w":1035,"h":713,"resize":"fit"},"large":{"w":1035,"h":713,"resize":"fit"},"small":{"w":680,"h":468,"resize":"fit"},"thumb":{"w":150,"h":150,"resize":"crop"}}}]}},"quote_count":8,"reply_count":2,"retweet_count":67,"favorite_count":102,"entities":{"hashtags":[],"urls":[{"url":"https:\/\/t.co\/41jXPAC1gp","expanded_url":"https:\/\/twitter.com\/i\/web\/status\/1228978876639875072","display_url":"twitter.com\/i\/web\/status\/1\u2026","indices":[117,140]}],"user_mentions":[],"symbols":[]},"favorited":false,"retweeted":false,"possibly_sensitive":false,"filter_level":"low","lang":"ja"},"quoted_status_id":1228556843057725441,"quoted_status_id_str":"1228556843057725441","quoted_status":{"created_at":"Sat Feb 15 05:49:11 +0000 2020","id":1228556843057725441,"id_str":"1228556843057725441","text":"\u91cd\u8981\u306a\u306e\u3067\u8981\u7d04\u3059\u308b\u3002\u6b66\u6f22\u533b\u5e2b\u304c\u82f1\u56fd\u306e\u89aa\u65cf\u306b\u8a9e\u3063\u305f\u5185\u5bb9\u306b\u3088\u308b\u3068\u3001\u30b3\u30ed\u30ca\u30a6\u30a3\u30eb\u30b9\u6cbb\u7652\u5f8c\u306b2\u5ea6\u76ee\u306b\u611f\u67d3\u3059\u308b\u5834\u5408\u304c\u3042\u308a\u3001\u4e00\u5ea6\u76ee\u306e\u6cbb\u7642\u85ac\u304c\u5fc3\u81d3\u7d44\u7e54\u306b\u4e0e\u3048\u305f\u30c0\u30e1\u30fc\u30b8\u3067\u3001\u6297\u4f53\u304c\u6a5f\u80fd\u305b\u305a\u5fc3\u75be\u60a3\u306b\u3088\u308a\u7a81\u7136\u6b7b\u3059\u308b\u30b1\u30fc\u30b9\u304c\u3042\u308b\u3002\uff08\u7d9a\u300cExclusive\u2026 https:\/\/t.co\/NDnC0FfX14","source":"\u003ca href=\"http:\/\/twitter.com\/download\/iphone\" rel=\"nofollow\"\u003eTwitter for iPhone\u003c\/a\u003e","truncated":true,"in_reply_to_status_id":null,"in_reply_to_status_id_str":null,"in_reply_to_user_id":null,"in_reply_to_user_id_str":null,"in_reply_to_screen_name":null,"user":{"id":509922519,"id_str":"509922519","name":"\u68ee\u5ca1\u6b63\u535a","screen_name":"Sukuitohananika","location":"\u30a6\u30a7\u30d6\u30b5\u30a4\u30c8\u2192","url":"http:\/\/www.lifestudies.org\/jp","description":"\u54f2\u5b66\u8005\u3002\u65e9\u7a32\u7530\u5927\u5b66\u4eba\u9593\u79d1\u5b66\u90e8\u6559\u6388\u3002\u751f\u547d\u306e\u54f2\u5b66\u3001\u5f62\u800c\u4e0a\u5b66\u3001\u751f\u547d\u5b66\u3001\u502b\u7406\u5b66\u3002\u300e\u7121\u75db\u6587\u660e\u8ad6\u300f\u300e\u307e\u3093\u304c\u54f2\u5b66\u5165\u9580\u300f\u300e\u611f\u3058\u306a\u3044\u7537\u300f\u300e\u5b97\u6559\u306a\u304d\u6642\u4ee3\u3092\u751f\u304d\u308b\u305f\u3081\u306b\u300f\u3002\u751f\u547d\u306e\u54f2\u5b66\u306b\u3064\u3044\u3066\u306e\u672c\u3092\u57f7\u7b46\u4e2d\u3002Masahiro Morioka. Philosopher. Professor, Waseda University.","translator_type":"none","protected":false,"verified":false,"followers_count":15158,"friends_count":155,"listed_count":724,"favourites_count":25,"statuses_count":25412,"created_at":"Thu Mar 01 08:33:53 +0000 2012","utc_offset":null,"time_zone":null,"geo_enabled":false,"lang":null,"contributors_enabled":false,"is_translator":false,"profile_background_color":"9AE4E8","profile_background_image_url":"http:\/\/abs.twimg.com\/images\/themes\/theme16\/bg.gif","profile_background_image_url_https":"https:\/\/abs.twimg.com\/images\/themes\/theme16\/bg.gif","profile_background_tile":false,"profile_link_color":"0084B4","profile_sidebar_border_color":"BDDCAD","profile_sidebar_fill_color":"DDFFCC","profile_text_color":"333333","profile_use_background_image":true,"profile_image_url":"http:\/\/pbs.twimg.com\/profile_images\/1005425357774729219\/J5qrarEc_normal.jpg","profile_image_url_https":"https:\/\/pbs.twimg.com\/profile_images\/1005425357774729219\/J5qrarEc_normal.jpg","profile_banner_url":"https:\/\/pbs.twimg.com\/profile_banners\/509922519\/1373647669","default_profile":false,"default_profile_image":false,"following":null,"follow_request_sent":null,"notifications":null},"geo":null,"coordinates":null,"place":null,"contributors":null,"is_quote_status":false,"extended_tweet":{"full_text":"\u91cd\u8981\u306a\u306e\u3067\u8981\u7d04\u3059\u308b\u3002\u6b66\u6f22\u533b\u5e2b\u304c\u82f1\u56fd\u306e\u89aa\u65cf\u306b\u8a9e\u3063\u305f\u5185\u5bb9\u306b\u3088\u308b\u3068\u3001\u30b3\u30ed\u30ca\u30a6\u30a3\u30eb\u30b9\u6cbb\u7652\u5f8c\u306b2\u5ea6\u76ee\u306b\u611f\u67d3\u3059\u308b\u5834\u5408\u304c\u3042\u308a\u3001\u4e00\u5ea6\u76ee\u306e\u6cbb\u7642\u85ac\u304c\u5fc3\u81d3\u7d44\u7e54\u306b\u4e0e\u3048\u305f\u30c0\u30e1\u30fc\u30b8\u3067\u3001\u6297\u4f53\u304c\u6a5f\u80fd\u305b\u305a\u5fc3\u75be\u60a3\u306b\u3088\u308a\u7a81\u7136\u6b7b\u3059\u308b\u30b1\u30fc\u30b9\u304c\u3042\u308b\u3002\uff08\u7d9a\u300cExclusive: Chinese doctors say Wuhan coronavi https:\/\/t.co\/lzxlbrTMQ0","display_text_range":[0,175],"entities":{"hashtags":[],"urls":[{"url":"https:\/\/t.co\/lzxlbrTMQ0","expanded_url":"https:\/\/www.taiwannews.com.tw\/en\/news\/3876197","display_url":"taiwannews.com.tw\/en\/news\/3876197","indices":[152,175]}],"user_mentions":[],"symbols":[]}},"quote_count":304,"reply_count":48,"retweet_count":5311,"favorite_count":6493,"entities":{"hashtags":[],"urls":[{"url":"https:\/\/t.co\/NDnC0FfX14","expanded_url":"https:\/\/twitter.com\/i\/web\/status\/1228556843057725441","display_url":"twitter.com\/i\/web\/status\/1\u2026","indices":[117,140]}],"user_mentions":[],"symbols":[]},"favorited":false,"retweeted":false,"possibly_sensitive":false,"filter_level":"low","lang":"ja"},"quoted_status_permalink":{"url":"https:\/\/t.co\/7OXhunLBNo","expanded":"https:\/\/twitter.com\/Sukuitohananika\/status\/1228556843057725441","display":"twitter.com\/Sukuitohananik\u2026"},"is_quote_status":true,"quote_count":0,"reply_count":0,"retweet_count":0,"favorite_count":0,"entities":{"hashtags":[],"urls":[],"user_mentions":[{"screen_name":"cjhiking","name":"motihamotiya2","id":703868384174145536,"id_str":"703868384174145536","indices":[3,12]}],"symbols":[]},"favorited":false,"retweeted":false,"filter_level":"low","lang":"ja","timestamp_ms":"1581890301337"}
