{"created_at":"Sun Feb 16 21:54:50 +0000 2020","id":1229162244820193280,"id_str":"1229162244820193280","text":"RT @yk_haretoke: \u62dd\u5553 Love music\u69d8\n\u3044\u3064\u3082\u304a\u4e16\u8a71\u306b\u306a\u3063\u3066\u304a\u308a\u307e\u3059\u3002\u307e\u305f\u3044\u3064\u306e\u65e5\u304bSOLIDEMO\u3092\u30b9\u30bf\u30b8\u30aa\u30b2\u30b9\u30c8\u3067\u547c\u3093\u3067\u304f\u3060\u3055\u308b\u3053\u3068\u3092\u5207\u306b\u9858\u3063\u3066\u304a\u308a\u307e\u3059\u3002\u4f55\u5352\u5b9c\u3057\u304f\u304a\u9858\u3044\u81f4\u3057\u307e\u3059\u3002\n#Lovemusic\n#LoveYourself\nhttps:\/\/t\u2026","source":"\u003ca href=\"http:\/\/twitter.com\/download\/iphone\" rel=\"nofollow\"\u003eTwitter for iPhone\u003c\/a\u003e","truncated":false,"in_reply_to_status_id":null,"in_reply_to_status_id_str":null,"in_reply_to_user_id":null,"in_reply_to_user_id_str":null,"in_reply_to_screen_name":null,"user":{"id":1124613955089944577,"id_str":"1124613955089944577","name":"BIG BOSS YURIE","screen_name":"BByurie1","location":null,"url":null,"description":"\ud83d\udd25SOLIDEMO\ud83d\udd25\ud83d\udc36\ud83d\udc9a\ud83d\udc99\u6b4c\u58f0\u3001\u5168\u3066\u304c\u5927\u597d\u304d\ud83d\udc51 W\u63a8\u3057\u2764\ufe0f\u2605 \u6771\u4eaccollars\uff0a\u53cc\u5b50collars\uff0a","translator_type":"none","protected":false,"verified":false,"followers_count":54,"friends_count":66,"listed_count":1,"favourites_count":1837,"statuses_count":1620,"created_at":"Sat May 04 09:57:16 +0000 2019","utc_offset":null,"time_zone":null,"geo_enabled":false,"lang":null,"contributors_enabled":false,"is_translator":false,"profile_background_color":"F5F8FA","profile_background_image_url":"","profile_background_image_url_https":"","profile_background_tile":false,"profile_link_color":"1DA1F2","profile_sidebar_border_color":"C0DEED","profile_sidebar_fill_color":"DDEEF6","profile_text_color":"333333","profile_use_background_image":true,"profile_image_url":"http:\/\/pbs.twimg.com\/profile_images\/1203121264929333250\/uSdUBFoM_normal.jpg","profile_image_url_https":"https:\/\/pbs.twimg.com\/profile_images\/1203121264929333250\/uSdUBFoM_normal.jpg","profile_banner_url":"https:\/\/pbs.twimg.com\/profile_banners\/1124613955089944577\/1568331303","default_profile":true,"default_profile_image":false,"following":null,"follow_request_sent":null,"notifications":null},"geo":null,"coordinates":null,"place":null,"contributors":null,"retweeted_status":{"created_at":"Sun Feb 16 16:31:05 +0000 2020","id":1229080769726832640,"id_str":"1229080769726832640","text":"\u62dd\u5553 Love music\u69d8\n\u3044\u3064\u3082\u304a\u4e16\u8a71\u306b\u306a\u3063\u3066\u304a\u308a\u307e\u3059\u3002\u307e\u305f\u3044\u3064\u306e\u65e5\u304bSOLIDEMO\u3092\u30b9\u30bf\u30b8\u30aa\u30b2\u30b9\u30c8\u3067\u547c\u3093\u3067\u304f\u3060\u3055\u308b\u3053\u3068\u3092\u5207\u306b\u9858\u3063\u3066\u304a\u308a\u307e\u3059\u3002\u4f55\u5352\u5b9c\u3057\u304f\u304a\u9858\u3044\u81f4\u3057\u307e\u3059\u3002\n#Lovemusic\n#LoveYourself\u2026 https:\/\/t.co\/cyEydHNjxu","display_text_range":[0,140],"source":"\u003ca href=\"http:\/\/twitter.com\/download\/android\" rel=\"nofollow\"\u003eTwitter for Android\u003c\/a\u003e","truncated":true,"in_reply_to_status_id":null,"in_reply_to_status_id_str":null,"in_reply_to_user_id":null,"in_reply_to_user_id_str":null,"in_reply_to_screen_name":null,"user":{"id":135419099,"id_str":"135419099","name":"\u3086\u304d","screen_name":"yk_haretoke","location":null,"url":null,"description":"This is a kind of love","translator_type":"none","protected":false,"verified":false,"followers_count":525,"friends_count":728,"listed_count":24,"favourites_count":14742,"statuses_count":139623,"created_at":"Wed Apr 21 07:28:39 +0000 2010","utc_offset":null,"time_zone":null,"geo_enabled":true,"lang":null,"contributors_enabled":false,"is_translator":false,"profile_background_color":"ACDED6","profile_background_image_url":"http:\/\/abs.twimg.com\/images\/themes\/theme18\/bg.gif","profile_background_image_url_https":"https:\/\/abs.twimg.com\/images\/themes\/theme18\/bg.gif","profile_background_tile":false,"profile_link_color":"038543","profile_sidebar_border_color":"EEEEEE","profile_sidebar_fill_color":"F6F6F6","profile_text_color":"333333","profile_use_background_image":true,"profile_image_url":"http:\/\/pbs.twimg.com\/profile_images\/1186995520192958465\/-y2KKxqM_normal.jpg","profile_image_url_https":"https:\/\/pbs.twimg.com\/profile_images\/1186995520192958465\/-y2KKxqM_normal.jpg","profile_banner_url":"https:\/\/pbs.twimg.com\/profile_banners\/135419099\/1565374544","default_profile":false,"default_profile_image":false,"following":null,"follow_request_sent":null,"notifications":null},"geo":null,"coordinates":null,"place":null,"contributors":null,"is_quote_status":false,"extended_tweet":{"full_text":"\u62dd\u5553 Love music\u69d8\n\u3044\u3064\u3082\u304a\u4e16\u8a71\u306b\u306a\u3063\u3066\u304a\u308a\u307e\u3059\u3002\u307e\u305f\u3044\u3064\u306e\u65e5\u304bSOLIDEMO\u3092\u30b9\u30bf\u30b8\u30aa\u30b2\u30b9\u30c8\u3067\u547c\u3093\u3067\u304f\u3060\u3055\u308b\u3053\u3068\u3092\u5207\u306b\u9858\u3063\u3066\u304a\u308a\u307e\u3059\u3002\u4f55\u5352\u5b9c\u3057\u304f\u304a\u9858\u3044\u81f4\u3057\u307e\u3059\u3002\n#Lovemusic\n#LoveYourself\nhttps:\/\/t.co\/Qgs0AY5Fa1 https:\/\/t.co\/1im7zitNUV","display_text_range":[0,136],"entities":{"hashtags":[{"text":"Lovemusic","indices":[88,98]},{"text":"LoveYourself","indices":[99,112]}],"urls":[{"url":"https:\/\/t.co\/Qgs0AY5Fa1","expanded_url":"https:\/\/natalie.mu\/music\/gallery\/news\/220249\/655633","display_url":"natalie.mu\/music\/gallery\/\u2026","indices":[113,136]}],"user_mentions":[],"symbols":[],"media":[{"id":1229080764119052288,"id_str":"1229080764119052288","indices":[137,160],"media_url":"http:\/\/pbs.twimg.com\/media\/EQ6ScWmU8AAUZkm.jpg","media_url_https":"https:\/\/pbs.twimg.com\/media\/EQ6ScWmU8AAUZkm.jpg","url":"https:\/\/t.co\/1im7zitNUV","display_url":"pic.twitter.com\/1im7zitNUV","expanded_url":"https:\/\/twitter.com\/yk_haretoke\/status\/1229080769726832640\/photo\/1","type":"photo","sizes":{"medium":{"w":1200,"h":789,"resize":"fit"},"small":{"w":680,"h":447,"resize":"fit"},"thumb":{"w":150,"h":150,"resize":"crop"},"large":{"w":1440,"h":947,"resize":"fit"}}}]},"extended_entities":{"media":[{"id":1229080764119052288,"id_str":"1229080764119052288","indices":[137,160],"media_url":"http:\/\/pbs.twimg.com\/media\/EQ6ScWmU8AAUZkm.jpg","media_url_https":"https:\/\/pbs.twimg.com\/media\/EQ6ScWmU8AAUZkm.jpg","url":"https:\/\/t.co\/1im7zitNUV","display_url":"pic.twitter.com\/1im7zitNUV","expanded_url":"https:\/\/twitter.com\/yk_haretoke\/status\/1229080769726832640\/photo\/1","type":"photo","sizes":{"medium":{"w":1200,"h":789,"resize":"fit"},"small":{"w":680,"h":447,"resize":"fit"},"thumb":{"w":150,"h":150,"resize":"crop"},"large":{"w":1440,"h":947,"resize":"fit"}}}]}},"quote_count":0,"reply_count":1,"retweet_count":10,"favorite_count":13,"entities":{"hashtags":[{"text":"Lovemusic","indices":[88,98]},{"text":"LoveYourself","indices":[99,112]}],"urls":[{"url":"https:\/\/t.co\/cyEydHNjxu","expanded_url":"https:\/\/twitter.com\/i\/web\/status\/1229080769726832640","display_url":"twitter.com\/i\/web\/status\/1\u2026","indices":[114,137]}],"user_mentions":[],"symbols":[]},"favorited":false,"retweeted":false,"possibly_sensitive":false,"filter_level":"low","lang":"ja"},"is_quote_status":false,"quote_count":0,"reply_count":0,"retweet_count":0,"favorite_count":0,"entities":{"hashtags":[{"text":"Lovemusic","indices":[105,115]},{"text":"LoveYourself","indices":[116,129]}],"urls":[],"user_mentions":[{"screen_name":"yk_haretoke","name":"\u3086\u304d","id":135419099,"id_str":"135419099","indices":[3,15]}],"symbols":[]},"favorited":false,"retweeted":false,"filter_level":"low","lang":"ja","timestamp_ms":"1581890090552"}
