{"created_at":"Sun Feb 16 21:51:37 +0000 2020","id":1229161434803843072,"id_str":"1229161434803843072","text":"Great news for a lovely lad......well done Lewis..sorry I missed that century goal!!","source":"\u003ca href=\"https:\/\/mobile.twitter.com\" rel=\"nofollow\"\u003eTwitter Web App\u003c\/a\u003e","truncated":false,"in_reply_to_status_id":null,"in_reply_to_status_id_str":null,"in_reply_to_user_id":null,"in_reply_to_user_id_str":null,"in_reply_to_screen_name":null,"user":{"id":1007174724999360512,"id_str":"1007174724999360512","name":"Eddiew80Oct","screen_name":"eddiew79oct","location":"North East, England","url":null,"description":"A very proud Grandad of 4 great Grandkids","translator_type":"none","protected":false,"verified":false,"followers_count":65,"friends_count":71,"listed_count":1,"favourites_count":11854,"statuses_count":6011,"created_at":"Thu Jun 14 08:15:41 +0000 2018","utc_offset":null,"time_zone":null,"geo_enabled":false,"lang":null,"contributors_enabled":false,"is_translator":false,"profile_background_color":"F5F8FA","profile_background_image_url":"","profile_background_image_url_https":"","profile_background_tile":false,"profile_link_color":"1DA1F2","profile_sidebar_border_color":"C0DEED","profile_sidebar_fill_color":"DDEEF6","profile_text_color":"333333","profile_use_background_image":true,"profile_image_url":"http:\/\/pbs.twimg.com\/profile_images\/1226224817432596480\/Ky_6PvlG_normal.jpg","profile_image_url_https":"https:\/\/pbs.twimg.com\/profile_images\/1226224817432596480\/Ky_6PvlG_normal.jpg","profile_banner_url":"https:\/\/pbs.twimg.com\/profile_banners\/1007174724999360512\/1569707133","default_profile":true,"default_profile_image":false,"following":null,"follow_request_sent":null,"notifications":null},"geo":null,"coordinates":null,"place":null,"contributors":null,"quoted_status_id":1229023855521468416,"quoted_status_id_str":"1229023855521468416","quoted_status":{"created_at":"Sun Feb 16 12:44:55 +0000 2020","id":1229023855521468416,"id_str":"1229023855521468416","text":"Thank you @FC_Hartlepool \u26bd\ufe0f\u26bd\ufe0f\u26bd\ufe0f\n\nFantastic club to be part of \ud83d\ude0a\n\n@ClaveringBolt https:\/\/t.co\/AjWPiBpsKJ","display_text_range":[0,79],"source":"\u003ca href=\"http:\/\/twitter.com\/download\/android\" rel=\"nofollow\"\u003eTwitter for Android\u003c\/a\u003e","truncated":false,"in_reply_to_status_id":null,"in_reply_to_status_id_str":null,"in_reply_to_user_id":null,"in_reply_to_user_id_str":null,"in_reply_to_screen_name":null,"user":{"id":570713870,"id_str":"570713870","name":"Carley Campbell","screen_name":"CarleyRaine","location":null,"url":null,"description":null,"translator_type":"none","protected":false,"verified":false,"followers_count":38,"friends_count":73,"listed_count":0,"favourites_count":2445,"statuses_count":357,"created_at":"Fri May 04 10:25:18 +0000 2012","utc_offset":null,"time_zone":null,"geo_enabled":true,"lang":null,"contributors_enabled":false,"is_translator":false,"profile_background_color":"C0DEED","profile_background_image_url":"http:\/\/abs.twimg.com\/images\/themes\/theme1\/bg.png","profile_background_image_url_https":"https:\/\/abs.twimg.com\/images\/themes\/theme1\/bg.png","profile_background_tile":false,"profile_link_color":"1DA1F2","profile_sidebar_border_color":"C0DEED","profile_sidebar_fill_color":"DDEEF6","profile_text_color":"333333","profile_use_background_image":true,"profile_image_url":"http:\/\/pbs.twimg.com\/profile_images\/1171150817962995712\/goEISLrk_normal.jpg","profile_image_url_https":"https:\/\/pbs.twimg.com\/profile_images\/1171150817962995712\/goEISLrk_normal.jpg","profile_banner_url":"https:\/\/pbs.twimg.com\/profile_banners\/570713870\/1566319315","default_profile":true,"default_profile_image":false,"following":null,"follow_request_sent":null,"notifications":null},"geo":null,"coordinates":null,"place":null,"contributors":null,"is_quote_status":false,"quote_count":0,"reply_count":2,"retweet_count":1,"favorite_count":13,"entities":{"hashtags":[],"urls":[],"user_mentions":[{"screen_name":"FC_Hartlepool","name":"FC Hartlepool","id":332971333,"id_str":"332971333","indices":[10,24]},{"screen_name":"ClaveringBolt","name":"Clavering PESSPA \/ N C McAvoy","id":3370757860,"id_str":"3370757860","indices":[65,79]}],"symbols":[],"media":[{"id":1229023834923245569,"id_str":"1229023834923245569","indices":[80,103],"media_url":"http:\/\/pbs.twimg.com\/media\/EQ5eqo0WoAEsbtT.jpg","media_url_https":"https:\/\/pbs.twimg.com\/media\/EQ5eqo0WoAEsbtT.jpg","url":"https:\/\/t.co\/AjWPiBpsKJ","display_url":"pic.twitter.com\/AjWPiBpsKJ","expanded_url":"https:\/\/twitter.com\/CarleyRaine\/status\/1229023855521468416\/photo\/1","type":"photo","sizes":{"thumb":{"w":150,"h":150,"resize":"crop"},"medium":{"w":1075,"h":926,"resize":"fit"},"small":{"w":680,"h":586,"resize":"fit"},"large":{"w":1075,"h":926,"resize":"fit"}}}]},"extended_entities":{"media":[{"id":1229023834923245569,"id_str":"1229023834923245569","indices":[80,103],"media_url":"http:\/\/pbs.twimg.com\/media\/EQ5eqo0WoAEsbtT.jpg","media_url_https":"https:\/\/pbs.twimg.com\/media\/EQ5eqo0WoAEsbtT.jpg","url":"https:\/\/t.co\/AjWPiBpsKJ","display_url":"pic.twitter.com\/AjWPiBpsKJ","expanded_url":"https:\/\/twitter.com\/CarleyRaine\/status\/1229023855521468416\/photo\/1","type":"photo","sizes":{"thumb":{"w":150,"h":150,"resize":"crop"},"medium":{"w":1075,"h":926,"resize":"fit"},"small":{"w":680,"h":586,"resize":"fit"},"large":{"w":1075,"h":926,"resize":"fit"}}},{"id":1229023849267826688,"id_str":"1229023849267826688","indices":[80,103],"media_url":"http:\/\/pbs.twimg.com\/media\/EQ5ereQXkAA21GO.jpg","media_url_https":"https:\/\/pbs.twimg.com\/media\/EQ5ereQXkAA21GO.jpg","url":"https:\/\/t.co\/AjWPiBpsKJ","display_url":"pic.twitter.com\/AjWPiBpsKJ","expanded_url":"https:\/\/twitter.com\/CarleyRaine\/status\/1229023855521468416\/photo\/1","type":"photo","sizes":{"large":{"w":1072,"h":1043,"resize":"fit"},"thumb":{"w":150,"h":150,"resize":"crop"},"medium":{"w":1072,"h":1043,"resize":"fit"},"small":{"w":680,"h":662,"resize":"fit"}}}]},"favorited":false,"retweeted":false,"possibly_sensitive":false,"filter_level":"low","lang":"en"},"quoted_status_permalink":{"url":"https:\/\/t.co\/o5QhdRxWFJ","expanded":"https:\/\/twitter.com\/CarleyRaine\/status\/1229023855521468416","display":"twitter.com\/CarleyRaine\/st\u2026"},"is_quote_status":true,"quote_count":0,"reply_count":0,"retweet_count":0,"favorite_count":0,"entities":{"hashtags":[],"urls":[],"user_mentions":[],"symbols":[]},"favorited":false,"retweeted":false,"filter_level":"low","lang":"en","timestamp_ms":"1581889897429"}
