{"created_at":"Sun Feb 16 21:51:26 +0000 2020","id":1229161389400502272,"id_str":"1229161389400502272","text":"@hillcity Don't make us use Facebook for anything, share product news","display_text_range":[10,69],"source":"\u003ca href=\"http:\/\/twitter.com\/download\/android\" rel=\"nofollow\"\u003eTwitter for Android\u003c\/a\u003e","truncated":false,"in_reply_to_status_id":1229157578426343426,"in_reply_to_status_id_str":"1229157578426343426","in_reply_to_user_id":932103948709675008,"in_reply_to_user_id_str":"932103948709675008","in_reply_to_screen_name":"hillcity","user":{"id":41334492,"id_str":"41334492","name":"Kyle Rusche","screen_name":"kr1111","location":"Pittsburgh, PA","url":null,"description":null,"translator_type":"none","protected":false,"verified":false,"followers_count":48,"friends_count":211,"listed_count":1,"favourites_count":251,"statuses_count":1053,"created_at":"Wed May 20 10:44:56 +0000 2009","utc_offset":null,"time_zone":null,"geo_enabled":true,"lang":null,"contributors_enabled":false,"is_translator":false,"profile_background_color":"709397","profile_background_image_url":"http:\/\/abs.twimg.com\/images\/themes\/theme6\/bg.gif","profile_background_image_url_https":"https:\/\/abs.twimg.com\/images\/themes\/theme6\/bg.gif","profile_background_tile":false,"profile_link_color":"FF3300","profile_sidebar_border_color":"86A4A6","profile_sidebar_fill_color":"A0C5C7","profile_text_color":"333333","profile_use_background_image":true,"profile_image_url":"http:\/\/pbs.twimg.com\/profile_images\/3100162777\/562cb1c91ff923b98b9b309cd9253556_normal.jpeg","profile_image_url_https":"https:\/\/pbs.twimg.com\/profile_images\/3100162777\/562cb1c91ff923b98b9b309cd9253556_normal.jpeg","profile_banner_url":"https:\/\/pbs.twimg.com\/profile_banners\/41334492\/1358021890","default_profile":false,"default_profile_image":false,"following":null,"follow_request_sent":null,"notifications":null},"geo":null,"coordinates":null,"place":null,"contributors":null,"is_quote_status":false,"quote_count":0,"reply_count":0,"retweet_count":0,"favorite_count":0,"entities":{"hashtags":[],"urls":[],"user_mentions":[{"screen_name":"hillcity","name":"Hill City","id":932103948709675008,"id_str":"932103948709675008","indices":[0,9]}],"symbols":[]},"favorited":false,"retweeted":false,"filter_level":"low","lang":"en","timestamp_ms":"1581889886604"}
