{"created_at":"Sun Feb 16 21:47:46 +0000 2020","id":1229160464241786880,"id_str":"1229160464241786880","text":"@MarkDice Bc the fake news media all live in fantasy worlds \ud83e\udd37\u200d\u2640\ufe0f\ud83e\udd26\u200d\u2640\ufe0f\ud83d\ude02","display_text_range":[10,69],"source":"\u003ca href=\"http:\/\/twitter.com\/download\/iphone\" rel=\"nofollow\"\u003eTwitter for iPhone\u003c\/a\u003e","truncated":false,"in_reply_to_status_id":1229139119030161408,"in_reply_to_status_id_str":"1229139119030161408","in_reply_to_user_id":35039490,"in_reply_to_user_id_str":"35039490","in_reply_to_screen_name":"MarkDice","user":{"id":2883473717,"id_str":"2883473717","name":"Marie Tackett\ud83c\uddfa\ud83c\uddf8","screen_name":"marieatackett","location":"Kentucky, USA","url":null,"description":"Proud Mother of 2 boys! AirForce Mom. America First! 2A Supporter & Defender! Conservative. Pro-Life. \ud83d\udeabDM","translator_type":"none","protected":false,"verified":false,"followers_count":2171,"friends_count":2522,"listed_count":35,"favourites_count":120420,"statuses_count":100840,"created_at":"Wed Nov 19 01:46:03 +0000 2014","utc_offset":null,"time_zone":null,"geo_enabled":true,"lang":null,"contributors_enabled":false,"is_translator":false,"profile_background_color":"C0DEED","profile_background_image_url":"http:\/\/abs.twimg.com\/images\/themes\/theme1\/bg.png","profile_background_image_url_https":"https:\/\/abs.twimg.com\/images\/themes\/theme1\/bg.png","profile_background_tile":false,"profile_link_color":"1DA1F2","profile_sidebar_border_color":"C0DEED","profile_sidebar_fill_color":"DDEEF6","profile_text_color":"333333","profile_use_background_image":true,"profile_image_url":"http:\/\/pbs.twimg.com\/profile_images\/1226584802968686593\/kA7iBQgu_normal.jpg","profile_image_url_https":"https:\/\/pbs.twimg.com\/profile_images\/1226584802968686593\/kA7iBQgu_normal.jpg","profile_banner_url":"https:\/\/pbs.twimg.com\/profile_banners\/2883473717\/1581275581","default_profile":true,"default_profile_image":false,"following":null,"follow_request_sent":null,"notifications":null},"geo":null,"coordinates":null,"place":null,"contributors":null,"is_quote_status":false,"quote_count":0,"reply_count":0,"retweet_count":0,"favorite_count":0,"entities":{"hashtags":[],"urls":[],"user_mentions":[{"screen_name":"MarkDice","name":"Mark Dice","id":35039490,"id_str":"35039490","indices":[0,9]}],"symbols":[]},"favorited":false,"retweeted":false,"filter_level":"low","lang":"en","timestamp_ms":"1581889666029"}
